cxshll/__init__.py
cxshll-0.0.1.data/scripts/foo.sh
cxshll-0.0.1.dist-info/LICENSE
cxshll-0.0.1.dist-info/METADATA
cxshll-0.0.1.dist-info/WHEEL
cxshll-0.0.1.dist-info/top_level.txt
cxshll-0.0.1.dist-info/RECORD
